{
    "info": {
        "name": "TeachersBook API Tests",
        "description": "Коллекция тестов для TeachersBook REST API",
        "schema": "https://schema.getpostman.com/json/collection/v2.1.0/collection.json"
    },
    "item": [
        {
            "name": "Authentication",
            "item": [
                {
                    "name": "Login - Admin",
                    "request": {
                        "method": "POST",
                        "header": [
                            {
                                "key": "Content-Type",
                                "value": "application/json"
                            }
                        ],
                        "body": {
                            "mode": "raw",
                            "raw": "{\n  \"username\": \"admin\",\n  \"password\": \"admin\"\n}"
                        },
                        "url": {
                            "raw": "http://localhost:8181/api/auth/login",
                            "protocol": "http",
                            "host": [
                                "localhost"
                            ],
                            "port": "8181",
                            "path": [
                                "api",
                                "auth",
                                "login"
                            ]
                        }
                    },
                    "response": []
                },
                {
                    "name": "Login - Invalid Credentials",
                    "request": {
                        "method": "POST",
                        "header": [
                            {
                                "key": "Content-Type",
                                "value": "application/json"
                            }
                        ],
                        "body": {
                            "mode": "raw",
                            "raw": "{\n  \"username\": \"wronguser\",\n  \"password\": \"wrongpass\"\n}"
                        },
                        "url": {
                            "raw": "http://localhost:8181/api/auth/login",
                            "protocol": "http",
                            "host": [
                                "localhost"
                            ],
                            "port": "8181",
                            "path": [
                                "api",
                                "auth",
                                "login"
                            ]
                        }
                    },
                    "response": []
                },
                {
                    "name": "Register - New User",
                    "request": {
                        "method": "POST",
                        "header": [
                            {
                                "key": "Content-Type",
                                "value": "application/json"
                            }
                        ],
                        "body": {
                            "mode": "raw",
                            "raw": "{\n  \"username\": \"newuser\",\n  \"password\": \"password123\",\n  \"firstName\": \"Новый\",\n  \"lastName\": \"Пользователь\"\n}"
                        },
                        "url": {
                            "raw": "http://localhost:8181/api/auth/register",
                            "protocol": "http",
                            "host": [
                                "localhost"
                            ],
                            "port": "8181",
                            "path": [
                                "api",
                                "auth",
                                "register"
                            ]
                        }
                    },
                    "response": []
                }
            ]
        },
        {
            "name": "User Management",
            "item": [
                {
                    "name": "Generate Credentials",
                    "request": {
                        "method": "POST",
                        "header": [
                            {
                                "key": "Content-Type",
                                "value": "application/json"
                            }
                        ],
                        "body": {
                            "mode": "raw",
                            "raw": "{\n  \"firstName\": \"Иван\",\n  \"lastName\": \"Петров\"\n}"
                        },
                        "url": {
                            "raw": "http://localhost:8181/api/users/generate-credentials",
                            "protocol": "http",
                            "host": [
                                "localhost"
                            ],
                            "port": "8181",
                            "path": [
                                "api",
                                "users",
                                "generate-credentials"
                            ]
                        }
                    },
                    "response": []
                },
                {
                    "name": "Create Teacher",
                    "request": {
                        "method": "POST",
                        "header": [
                            {
                                "key": "Content-Type",
                                "value": "application/json"
                            }
                        ],
                        "body": {
                            "mode": "raw",
                            "raw": "{\n  \"username\": \"ivan.petrov\",\n  \"password\": \"ivan.petrov123\",\n  \"firstName\": \"Иван\",\n  \"lastName\": \"Петров\",\n  \"role\": \"TEACHER\"\n}"
                        },
                        "url": {
                            "raw": "http://localhost:8181/api/users",
                            "protocol": "http",
                            "host": [
                                "localhost"
                            ],
                            "port": "8181",
                            "path": [
                                "api",
                                "users"
                            ]
                        }
                    },
                    "response": []
                },
                {
                    "name": "Create Student",
                    "request": {
                        "method": "POST",
                        "header": [
                            {
                                "key": "Content-Type",
                                "value": "application/json"
                            }
                        ],
                        "body": {
                            "mode": "raw",
                            "raw": "{\n  \"username\": \"anna.sidorova\",\n  \"password\": \"anna.sidorova456\",\n  \"firstName\": \"Анна\",\n  \"lastName\": \"Сидорова\",\n  \"role\": \"STUDENT\"\n}"
                        },
                        "url": {
                            "raw": "http://localhost:8181/api/users",
                            "protocol": "http",
                            "host": [
                                "localhost"
                            ],
                            "port": "8181",
                            "path": [
                                "api",
                                "users"
                            ]
                        }
                    },
                    "response": []
                },
                {
                    "name": "Get All Teachers",
                    "request": {
                        "method": "GET",
                        "header": [],
                        "url": {
                            "raw": "http://localhost:8181/api/users/teachers",
                            "protocol": "http",
                            "host": [
                                "localhost"
                            ],
                            "port": "8181",
                            "path": [
                                "api",
                                "users",
                                "teachers"
                            ]
                        }
                    },
                    "response": []
                },
                {
                    "name": "Get All Students",
                    "request": {
                        "method": "GET",
                        "header": [],
                        "url": {
                            "raw": "http://localhost:8181/api/users/students",
                            "protocol": "http",
                            "host": [
                                "localhost"
                            ],
                            "port": "8181",
                            "path": [
                                "api",
                                "users",
                                "students"
                            ]
                        }
                    },
                    "response": []
                }
            ]
        },
        {
            "name": "Dashboard",
            "item": [
                {
                    "name": "Get Dashboard Stats",
                    "request": {
                        "method": "GET",
                        "header": [],
                        "url": {
                            "raw": "http://localhost:8181/api/dashboard/stats",
                            "protocol": "http",
                            "host": [
                                "localhost"
                            ],
                            "port": "8181",
                            "path": [
                                "api",
                                "dashboard",
                                "stats"
                            ]
                        }
                    },
                    "response": []
                }
            ]
        },
        {
            "name": "Students",
            "item": [
                {
                    "name": "Get All Students (Full Info)",
                    "request": {
                        "method": "GET",
                        "header": [],
                        "url": {
                            "raw": "http://localhost:8181/api/students",
                            "protocol": "http",
                            "host": [
                                "localhost"
                            ],
                            "port": "8181",
                            "path": [
                                "api",
                                "students"
                            ]
                        }
                    },
                    "response": []
                },
                {
                    "name": "Get Student By ID",
                    "request": {
                        "method": "GET",
                        "header": [],
                        "url": {
                            "raw": "http://localhost:8181/api/students/:id",
                            "protocol": "http",
                            "host": [
                                "localhost"
                            ],
                            "port": "8181",
                            "path": [
                                "api",
                                "students",
                                ":id"
                            ],
                            "variable": [
                                {
                                    "key": "id",
                                    "value": "1"
                                }
                            ]
                        }
                    },
                    "response": []
                },
                {
                    "name": "Create Student",
                    "request": {
                        "method": "POST",
                        "header": [
                            {
                                "key": "Content-Type",
                                "value": "application/json"
                            }
                        ],
                        "body": {
                            "mode": "raw",
                            "raw": "{\n  \"firstName\": \"Петр\",\n  \"lastName\": \"Сергеев\",\n  \"patronymic\": \"Иванович\",\n  \"phone\": \"+7 999 123 45 67\",\n  \"groupId\": 1\n}"
                        },
                        "url": {
                            "raw": "http://localhost:8181/api/students",
                            "protocol": "http",
                            "host": [
                                "localhost"
                            ],
                            "port": "8181",
                            "path": [
                                "api",
                                "students"
                            ]
                        }
                    },
                    "response": []
                }
            ]
        },
        {
            "name": "Subjects",
            "item": [
                {
                    "name": "Get All Subjects",
                    "request": {
                        "method": "GET",
                        "header": [],
                        "url": {
                            "raw": "http://localhost:8181/api/subjects",
                            "protocol": "http",
                            "host": [
                                "localhost"
                            ],
                            "port": "8181",
                            "path": [
                                "api",
                                "subjects"
                            ]
                        }
                    },
                    "response": []
                },
                {
                    "name": "Create Subject",
                    "request": {
                        "method": "POST",
                        "header": [
                            {
                                "key": "Content-Type",
                                "value": "application/json"
                            }
                        ],
                        "body": {
                            "mode": "raw",
                            "raw": "{\n  \"name\": \"Математика\",\n  \"lectureHours\": 36,\n  \"practiceHours\": 18,\n  \"labHours\": 0,\n  \"seminarHours\": 0\n}"
                        },
                        "url": {
                            "raw": "http://localhost:8181/api/subjects",
                            "protocol": "http",
                            "host": [
                                "localhost"
                            ],
                            "port": "8181",
                            "path": [
                                "api",
                                "subjects"
                            ]
                        }
                    },
                    "response": []
                }
            ]
        },
        {
            "name": "Groups",
            "item": [
                {
                    "name": "Get All Groups",
                    "request": {
                        "method": "GET",
                        "header": [],
                        "url": {
                            "raw": "http://localhost:8181/api/groups",
                            "protocol": "http",
                            "host": [
                                "localhost"
                            ],
                            "port": "8181",
                            "path": [
                                "api",
                                "groups"
                            ]
                        }
                    },
                    "response": []
                },
                {
                    "name": "Create Group",
                    "request": {
                        "method": "POST",
                        "header": [
                            {
                                "key": "Content-Type",
                                "value": "application/json"
                            }
                        ],
                        "body": {
                            "mode": "raw",
                            "raw": "{\n  \"name\": \"ИС-21\",\n  \"specialization\": \"Информационные системы\",\n  \"course\": 2,\n  \"startYear\": 2021\n}"
                        },
                        "url": {
                            "raw": "http://localhost:8181/api/groups",
                            "protocol": "http",
                            "host": [
                                "localhost"
                            ],
                            "port": "8181",
                            "path": [
                                "api",
                                "groups"
                            ]
                        }
                    },
                    "response": []
                }
            ]
        }
    ]
}